{"nodes": [{"id": "home_amir_rag_comparch_comparch_repo_clean_api_service_py", "label": "api_service.py", "file_type": "code", "source_file": "api_service.py", "source_location": "L1"}, {"id": "home_amir_rag_comparch_comparch_repo_clean_api_service_rationale_1", "label": "FastAPI WebSocket Service for Hybrid Search RAG Pipeline Simplified version that", "file_type": "rationale", "source_file": "api_service.py", "source_location": "L1"}], "edges": [{"source": "home_amir_rag_comparch_comparch_repo_clean_api_service_py", "target": "logging", "relation": "imports", "context": "import", "confidence": "EXTRACTED", "source_file": "api_service.py", "source_location": "L8", "weight": 1.0}, {"source": "home_amir_rag_comparch_comparch_repo_clean_api_service_py", "target": "fastapi", "relation": "imports_from", "context": "import", "confidence": "EXTRACTED", "source_file": "api_service.py", "source_location": "L10", "weight": 1.0}, {"source": "home_amir_rag_comparch_comparch_repo_clean_api_service_py", "target": "api_lifespan", "relation": "imports_from", "context": "import", "confidence": "EXTRACTED", "source_file": "api_service.py", "source_location": "L16", "weight": 1.0}, {"source": "home_amir_rag_comparch_comparch_repo_clean_api_service_py", "target": "api_routes", "relation": "imports_from", "context": "import", "confidence": "EXTRACTED", "source_file": "api_service.py", "source_location": "L17", "weight": 1.0}, {"source": "home_amir_rag_comparch_comparch_repo_clean_api_service_py", "target": "uvicorn", "relation": "imports", "context": "import", "confidence": "EXTRACTED", "source_file": "api_service.py", "source_location": "L31", "weight": 1.0}, {"source": "home_amir_rag_comparch_comparch_repo_clean_api_service_rationale_1", "target": "home_amir_rag_comparch_comparch_repo_clean_api_service_py", "relation": "rationale_for", "confidence": "EXTRACTED", "source_file": "api_service.py", "source_location": "L1", "weight": 1.0}], "raw_calls": []}